SeqMetrics/__init__.py
SeqMetrics/_cls.py
SeqMetrics/_main.py
SeqMetrics/_rgr.py
SeqMetrics/utils.py
SeqMetrics-1.3.4.dist-info/LICENCE.md
SeqMetrics-1.3.4.dist-info/METADATA
SeqMetrics-1.3.4.dist-info/WHEEL
SeqMetrics-1.3.4.dist-info/top_level.txt
SeqMetrics-1.3.4.dist-info/RECORD
